pytest_reserial/__init__.py
pytest_reserial/reserial.py
pytest_reserial/update_log.py
pytest_reserial-0.6.1.dist-info/entry_points.txt
pytest_reserial-0.6.1.dist-info/licenses/LICENSE
pytest_reserial-0.6.1.dist-info/WHEEL
pytest_reserial-0.6.1.dist-info/METADATA
pytest_reserial-0.6.1.dist-info/RECORD
