Metadata-Version: 2.4
Name: pytest-reserial
Version: 0.6.1
Summary: Pytest fixture for recording and replaying serial port traffic.
Keywords: serial,testing,logging,mocking,patching,stubbing,record,replay
Author-email: Alexander Bessman <alexander.bessman@gmail.com>
Requires-Python: >=3.9
Classifier: Programming Language :: Python :: 3
Classifier: Programming Language :: Python :: 3.9
Classifier: Programming Language :: Python :: 3.10
Classifier: Programming Language :: Python :: 3.11
Classifier: Programming Language :: Python :: 3.12
Classifier: Programming Language :: Python :: 3.13
Classifier: Programming Language :: Python :: 3.14
Classifier: Development Status :: 4 - Beta
Classifier: License :: OSI Approved :: MIT License
License-File: LICENSE
Requires-Dist: pytest
Requires-Dist: pyserial
Requires-Dist: black ; extra == "dev"
Requires-Dist: isort ; extra == "dev"
Requires-Dist: mypy ; extra == "dev"
Requires-Dist: ruff ; extra == "dev"
Requires-Dist: tox ; extra == "dev"
Requires-Dist: coverage ; extra == "test"
Project-URL: Home, https://github.com/bessman/pytest-reserial
Provides-Extra: dev
Provides-Extra: test
